README.md
setup.py
elonadl/Cleanup.py
elonadl/Desktop.py
elonadl/Download.py
elonadl/Extract.py
elonadl/Move.py
elonadl/__init__.py
elonadl/__main__.py
elonadl/cleanup.py
elonadl/desktop.py
elonadl/download.py
elonadl/extract.py
elonadl/move.py
elonadl/start_menu.py
elonadl.egg-info/PKG-INFO
elonadl.egg-info/SOURCES.txt
elonadl.egg-info/dependency_links.txt
elonadl.egg-info/requires.txt
elonadl.egg-info/top_level.txt