Metadata-Version: 2.2
Name: elonadl
Version: 0.1.19
Summary: A Installer to download and setup ElonaPlusCustom-GX on Windows.
Author: vichmartins
Requires-Python: >=3.10
Requires-Dist: pywin32
Requires-Dist: requests
Requires-Dist: winshell
Dynamic: author
Dynamic: description
Dynamic: description-content-type
Dynamic: requires-dist
Dynamic: requires-python
Dynamic: summary
